ed_optimization/__init__.py
ed_optimization/application/__init__.py
ed_optimization/application/common/__init__.py
ed_optimization/application/common/responses/__init__.py
ed_optimization/application/common/responses/base_response.py
ed_optimization/application/contracts/__init__.py
ed_optimization/application/contracts/infrastructure/__init__.py
ed_optimization/application/contracts/infrastructure/cache/__init__.py
ed_optimization/application/contracts/infrastructure/cache/abc_cache.py
ed_optimization/application/contracts/infrastructure/google/__init__.py
ed_optimization/application/contracts/infrastructure/google/abc_google_maps_route_api.py
ed_optimization/application/contracts/infrastructure/google/types.py
ed_optimization/application/contracts/infrastructure/message_queue/__init__.py
ed_optimization/application/contracts/infrastructure/message_queue/abc_rabbitmq_producers.py
ed_optimization/application/features/__init__.py
ed_optimization/application/features/order/__init__.py
ed_optimization/application/features/order/dtos/__init__.py
ed_optimization/application/features/order/dtos/calcualte_order_details_dto.py
ed_optimization/application/features/order/dtos/create_business_dto.py
ed_optimization/application/features/order/dtos/create_consumer_dto.py
ed_optimization/application/features/order/dtos/create_location_dto.py
ed_optimization/application/features/order/dtos/create_order_dto.py
ed_optimization/application/features/order/dtos/route_information_dto.py
ed_optimization/application/features/order/dtos/validators/__init__.py
ed_optimization/application/features/order/handlers/__init__.py
ed_optimization/application/features/order/handlers/commands/__init__.py
ed_optimization/application/features/order/handlers/commands/calculate_order_details_command_handler.py
ed_optimization/application/features/order/handlers/commands/process_order_command_handler.py
ed_optimization/application/features/order/handlers/queries/__init__.py
ed_optimization_service-0.2.2.dist-info/licenses/LICENSE
ed_optimization_service-0.2.2.dist-info/METADATA
ed_optimization_service-0.2.2.dist-info/WHEEL
ed_optimization_service-0.2.2.dist-info/top_level.txt
ed_optimization_service-0.2.2.dist-info/RECORD
